[
  {
    "image": "/images/appliances/AlmostForgotten.jpg",
    "title": "Almost Forgotten",
    "year": "1999",
    "link": ""
  },
  {
    "image": "/images/appliances/Alumiline.jpg",
    "title": "Alumiline",
    "year": "1999",
    "link": ""
  },
  {
    "image": "/images/appliances/Anna.jpg",
    "title": "Anna",
    "year": "1999",
    "link": ""
  },
  {
    "image": "/images/appliances/Appl.-I-Cant-Quite.jpg",
    "title": "Appl I Cant Quite",
    "year": "1999",
    "link": ""
  },
  {
    "image": "/images/appliances/Appliance.jpg",
    "title": "Appliance",
    "year": "1999",
    "link": ""
  },
  {
    "image": "/images/appliances/Appliances-for-the-Home.jpg",
    "title": "Appliances For The Home",
    "year": "1999",
    "link": ""
  },
  {
    "image": "/images/appliances/ASafePlace.jpg",
    "title": "A Safe Place",
    "year": "1999",
    "link": ""
  },
  {
    "image": "/images/appliances/AToolForTheMakingOfAHappyHome2.jpg",
    "title": "A Tool For The Making Of A Happy Home",
    "year": "1999",
    "link": ""
  },
  {
    "image": "/images/appliances/BackInThe-Day-e1435906997574.jpg",
    "title": "Back In The Day",
    "year": "1999",
    "link": ""
  },
  {
    "image": "/images/appliances/Centralia.jpg",
    "title": "Centralia",
    "year": "1999",
    "link": ""
  },
  {
    "image": "/images/appliances/convenience-795x1172.jpg",
    "title": "Convenience",
    "year": "1999",
    "link": ""
  },
  {
    "image": "/images/appliances/Cotidi-O-Mat.jpg",
    "title": "Cotidi O Mat",
    "year": "1999",
    "link": ""
  },
  {
    "image": "/images/appliances/Cozied-App.jpg",
    "title": "Cozied App",
    "year": "1999",
    "link": ""
  },
  {
    "image": "/images/appliances/crupik.jpg",
    "title": "Crupik",
    "year": "1999",
    "link": ""
  },
  {
    "image": "/images/appliances/Desk-Top.jpg",
    "title": "Desk Top",
    "year": "1999",
    "link": ""
  },
  {
    "image": "/images/appliances/Dispendere1-e1436157517810.jpg",
    "title": "Dispendere",
    "year": "1999",
    "link": ""
  },
  {
    "image": "/images/appliances/electromode.jpg",
    "title": "Electro Mode",
    "year": "1999",
    "link": ""
  },
  {
    "image": "/images/appliances/everyday-600x600.jpg",
    "title": "Everyday",
    "year": "1999",
    "link": ""
  },
  {
    "image": "/images/appliances/Foley1-683x1024.jpg",
    "title": "Foley",
    "year": "1999",
    "link": ""
  },
  {
    "image": "/images/appliances/gauge-795x805.jpg",
    "title": "Gauge",
    "year": "1999",
    "link": ""
  },
  {
    "image": "/images/appliances/HabliMat.jpg",
    "title": "Habli Mat",
    "year": "1999",
    "link": ""
  },
  {
    "image": "/images/appliances/Happiness.jpg",
    "title": "Happiness",
    "year": "1999",
    "link": ""
  },
  {
    "image": "/images/appliances/Household01-1024x768.jpg",
    "title": "Household",
    "year": "1999",
    "link": ""
  },
  {
    "image": "/images/appliances/housemate-795x522.jpg",
    "title": "Housemate",
    "year": "1999",
    "link": ""
  },
  {
    "image": "/images/appliances/Houseware.jpg",
    "title": "Houseware",
    "year": "1999",
    "link": ""
  },
  {
    "image": "/images/appliances/IMG_7010.jpg",
    "title": "An Appliance for the Remaking of a Happy Home or Bayberry, Bayberry, Bayberry",
    "year": "1999",
    "link": ""
  },
  {
    "image": "/images/appliances/IMG_8876.jpg",
    "title": "My Mother's Jetpacks",
    "year": "1999",
    "link": ""
  },
  {
    "image": "/images/appliances/LaborSavingDevi1Hi.jpg",
    "title": "Labor Saving Device",
    "year": "1999",
    "link": ""
  },
  {
    "image": "/images/appliances/Leezure-Life1.jpg",
    "title": "Leezure Life",
    "year": "1999",
    "link": ""
  },
  {
    "image": "/images/appliances/Like-Home.jpeg",
    "title": "Like Home",
    "year": "1999",
    "link": ""
  },
  {
    "image": "/images/appliances/loiss-795x1167.jpg",
    "title": "Loiss",
    "year": "1999",
    "link": ""
  },
  {
    "image": "/images/appliances/MetOMat.jpg",
    "title": "Met O Mat",
    "year": "1999",
    "link": ""
  },
  {
    "image": "/images/appliances/neotopus-795x785.jpg",
    "title": "Neotopus",
    "year": "1999",
    "link": ""
  },
  {
    "image": "/images/appliances/OnceFamiliar.jpg",
    "title": "Once Familiar",
    "year": "1999",
    "link": ""
  },
  {
    "image": "/images/appliances/SensitiveEquip.jpg",
    "title": "Sensitive Equip",
    "year": "1999",
    "link": ""
  },
  {
    "image": "/images/appliances/ShellysAppliance31-1024x695.jpg",
    "title": "Shellys Appliance",
    "year": "1999",
    "link": ""
  },
  {
    "image": "/images/appliances/Something1.jpg",
    "title": "Something",
    "year": "1999",
    "link": ""
  },
  {
    "image": "/images/appliances/Somethingelse1.jpg",
    "title": "Something Else",
    "year": "1999",
    "link": ""
  },
  {
    "image": "/images/appliances/Spat-O-Mat.jpg",
    "title": "Spat O Mat",
    "year": "1999",
    "link": ""
  },
  {
    "image": "/images/appliances/Sylvia.jpg",
    "title": "Sylvia",
    "year": "1999",
    "link": ""
  },
  {
    "image": "/images/appliances/Twin_b.jpg",
    "title": "Twin B",
    "year": "1999",
    "link": ""
  }
]
